ryvencore/AddOn.py
ryvencore/Base.py
ryvencore/Data.py
ryvencore/Flow.py
ryvencore/FlowExecutor.py
ryvencore/InfoMsgs.py
ryvencore/Node.py
ryvencore/NodePort.py
ryvencore/NodePortType.py
ryvencore/RC.py
ryvencore/README.md
ryvencore/Session.py
ryvencore/__init__.py
ryvencore/py.typed
ryvencore/utils.py
ryvencore/addons/Logging.py
ryvencore/addons/Variables.py
ryvencore/addons/__init__.py
ryvencore/addons/legacy/DTypes.py
ryvencore/addons/legacy/__init__.py
tests/__init__.py
tests/data_flow.py
tests/data_objects.py
tests/exec_flow.py
tests/logging-addon.py
tests/utils.py
tests/variables-addon.py
ryvencore-0.5.0.dist-info/LICENSE
ryvencore-0.5.0.dist-info/METADATA
ryvencore-0.5.0.dist-info/WHEEL
ryvencore-0.5.0.dist-info/top_level.txt
ryvencore-0.5.0.dist-info/RECORD
