Metadata-Version: 2.1
Name: ryvencore
Version: 0.5.0
Summary: Python backend for node editor-like graph-based processing
Home-page: https://github.com/leon-thomm/ryvencore
Author: Leon Thomm
Author-email: l.thomm@mailbox.org
Project-URL: Website, https://ryven.org
Classifier: Programming Language :: Python :: 3
Classifier: License :: OSI Approved :: GNU Lesser General Public License v2 or later (LGPLv2+)
Classifier: Operating System :: OS Independent
Requires-Python: >=3.7
License-File: LICENSE
Requires-Dist: packaging
Requires-Dist: importlib-metadata ; python_version < "3.8"
